{
	"credit": "Made with Blockbench by Mc_Jeronimo",
	"textures": {
		"particle": "blocks/quartz_block_side",
		"texture": "blocks/quartz_block_side"
	},
	"elements": [
		{
			"name": "Center post",
			"from": [7, 0, 0],
			"to": [9, 1, 6],
			"faces": {
				"north": {"uv": [6, 0, 8, 1], "texture": "#texture"},
				"east": {"uv": [6, 0, 12, 1], "texture": "#texture"},
				"west": {"uv": [6, 0, 12, 1], "texture": "#texture"},
				"up": {"uv": [6, 6, 8, 12], "texture": "#texture", "cullface": "up"},
				"down": {"uv": [6, 6, 8, 12], "texture": "#texture", "cullface": "down"}
			}
		},
		{
			"name": "Center post",
			"from": [7, 13, 0],
			"to": [9, 15, 6],
			"faces": {
				"north": {"uv": [6, 0, 8, 2], "texture": "#texture"},
				"east": {"uv": [6, 0, 12, 2], "texture": "#texture"},
				"west": {"uv": [6, 0, 12, 2], "texture": "#texture"},
				"up": {"uv": [6, 6, 8, 12], "texture": "#texture", "cullface": "up"},
				"down": {"uv": [6, 6, 8, 12], "texture": "#texture", "cullface": "down"}
			}
		},
		{
			"name": "Center post",
			"from": [7, 3, -8],
			"to": [9, 5, 1],
			"rotation": {"angle": 45, "axis": "x", "origin": [0, -4, 0]},
			"faces": {
				"east": {"uv": [6, 0, 15, 2], "texture": "#texture"},
				"west": {"uv": [6, 0, 15, 2], "texture": "#texture"},
				"up": {"uv": [6, 6, 8, 15], "texture": "#texture", "cullface": "up"},
				"down": {"uv": [6, 6, 8, 15], "texture": "#texture", "cullface": "down"}
			}
		},
		{
			"name": "Center post",
			"from": [7, -1.5, 3],
			"to": [9, 0.5, 12],
			"rotation": {"angle": -45, "axis": "x", "origin": [0, -4, 0]},
			"faces": {
				"east": {"uv": [6, 0, 15, 2], "texture": "#texture"},
				"west": {"uv": [6, 0, 15, 2], "texture": "#texture"},
				"up": {"uv": [6, 6, 8, 15], "texture": "#texture", "cullface": "up"},
				"down": {"uv": [6, 6, 8, 15], "texture": "#texture", "cullface": "down"}
			}
		},
		{
			"name": "Center post",
			"from": [7, 4.5, 3],
			"to": [9, 6.5, 12],
			"rotation": {"angle": -45, "axis": "x", "origin": [0, 2, 0]},
			"faces": {
				"east": {"uv": [6, 0, 15, 2], "texture": "#texture"},
				"west": {"uv": [6, 0, 15, 2], "texture": "#texture"},
				"up": {"uv": [6, 6, 8, 15], "texture": "#texture", "cullface": "up"},
				"down": {"uv": [6, 6, 8, 15], "texture": "#texture", "cullface": "down"}
			}
		},
		{
			"name": "Center post",
			"from": [7, 10, -6],
			"to": [9, 12, 4],
			"rotation": {"angle": 45, "axis": "x", "origin": [0, 6, 0]},
			"faces": {
				"east": {"uv": [6, 0, 16, 2], "texture": "#texture"},
				"west": {"uv": [6, 0, 16, 2], "texture": "#texture"},
				"up": {"uv": [6, 6, 8, 16], "texture": "#texture", "cullface": "up"},
				"down": {"uv": [6, 6, 8, 16], "texture": "#texture", "cullface": "down"}
			}
		}
	]
}